{"name":"Frosted Freak","description":"Frosted Freak is a Michigan hybrid that crosses Brand X with a long-lost sativa-dominant strain known as High Roller. She gets her name from the thick dusting of crystal resin that blankets its dense sage buds. With a citrus and piney mint flavor, Frosted Freak delivers potent effects that relax muscles, encourage the appetite, and calm nerves.","flavors":"1. Citrus, 2. Lime, 3. Vanilla","lineage":"","grow_metrics":"100-250, 7-9 wks","attributes_title":"Happy, Relaxed, Euphoric, Uplifted, Giggly, Stress, Depression, Pain, Insomnia, Muscle Spasms, Dry Eyes, Dry Mouth","attributes_num":"width:100%, width:78.544061302682%, width:73.5632183908046%, width:49.6168582375479%, width:49.6168582375479%, width:100%, width:76.824034334764%, width:37.9828326180258%, width:23.1759656652361%, width:20.3862660944206%, width:100%, width:100%"}