{"name":"Headband","description":"Meet Headband, the love-child of cannabis’ power couple, OG Kush and Sour Diesel. The smooth, creamy smoke is accented by flavors of lemons and diesel while the long-lasting effects are great for pain relief, helping you to relax, and to combat elevated stress levels. Many report that the effects create a slight pressure around the crown of their head and feels as though they are wearing a headband. The effects have been known to come on slow, so pace yourself with this potent hybrid. ","flavors":"1. Earthy, 2. Pungent, 3. Diesel","lineage":"","grow_metrics":"Difficult, .76-2 m, 251-500, 7-9 wks, > 200%","attributes_title":"Happy, Relaxed, Euphoric, Uplifted, Creative, Stress, Depression, Pain, Lack of Appetite, Headaches, Dry Mouth, Dry Eyes, Headache, Dizzy, Anxious","attributes_num":"width:100%, width:95.5232716869248%, width:80.978603995358%, width:79.5281621212791%, width:54.8748186118175%, width:100%, width:75.614976893649%, width:71.8473384960135%, width:42.7985481619995%, width:41.1854268087036%, width:100%, width:50.6818958720985%, width:28.5962992890055%, width:27.5181238322248%, width:22.4731663555813%"}