{"name":"Mission Kush","description":"Mission Kush by View Askew Farms is a powerful West Coast herb grown near the banks of the Columbia River. Bred from Silver Surfer and Haze, Mission Kush holds on to the earthy and herbaceous terpenes of its predecessors. The complementary effects of this sativa-dominant strain set in quickly, imbuing the consumer with a strong, positive focus that promotes productivity, long conversations, and mood elevation. Utilize Mission Kush to curb depression and mental fatigue while enhancing mood and productivity.   ","flavors":"1. Pine","lineage":"","grow_metrics":"","attributes_title":"Creative, Uplifted, Energetic, Euphoric, Happy, Muscle Spasms, Dry Eyes, Headache, Paranoid","attributes_num":"width:100%, width:66.6666666666667%, width:66.6666666666667%, width:66.6666666666667%, width:66.6666666666667%, width:100%, width:100%, width:100%, width:50%"}