{"name":"Monster OG","description":"Monster OG from The Green Element is a hybrid strain that crosses a heavy OG indica with an OG Kush and SFV OG hybrid. With a THC profile that can stretch past 26 percent, Monster OG’s effects come on strong to relax muscles, soothe pains, relieve stress, increase the appetite, and promote rest. Stout plants produce tights resin-packed buds that carry a blend of deep, earthy diesel and subtle burnt spice notes.","flavors":"1. Woody, 2. Pungent, 3. Skunk","lineage":"","grow_metrics":"7-9 wks","attributes_title":"Euphoric, Relaxed, Hungry, Creative, Happy, Stress, Fatigue, Pain, Insomnia, Lack of Appetite, Dry Mouth, Dry Eyes, Headache, Paranoid, Dizzy","attributes_num":"width:100%, width:97.8947368421053%, width:92.6315789473684%, width:86.3157894736842%, width:86.3157894736842%, width:100%, width:89.4736842105263%, width:26.3157894736842%, width:13.1578947368421%, width:12.5%, width:100%, width:54.9019607843137%, width:13.7254901960784%, width:13.7254901960784%, width:5.88235294117647%"}