{"name":"OG Diesel Kush","description":"OG Diesel Kush is a hybrid marijuana strain with frosty dark green buds. It has a THC content of up to 19.5% and CBD levels of up to 0.36%.","flavors":"1. Diesel, 2. Pine, 3. Skunk","lineage":"","grow_metrics":"","attributes_title":"Happy, Relaxed, Hungry, Focused, Uplifted, Stress, Pain, Headaches, Lack of Appetite, Depression, Dry Eyes, Dry Mouth, Paranoid, Dizzy, Headache","attributes_num":"width:100%, width:71.4971428571429%, width:58.3085714285714%, width:54.72%, width:34.5142857142857%, width:100%, width:81.646234676007%, width:79.0542907180385%, width:77.5831873905429%, width:74.2907180385289%, width:100%, width:72.100605496041%, width:6.59059152305543%, width:2.93432696786213%, width:0.978108989287378%"}