{"name":"Chocolate Diesel","description":"Chocolate Diesel is a sativa cannabis strain that brings together genetics from the original Sour Diesel and Chocolate Thai. With soaring euphoria that shoots straight to the head, Chocolate Diesel could easily be compared to a cup of coffee. Its flavors offer a little part of both parents, with notes of both earthy chocolate and skunky diesel.","flavors":"1. Nutty, 2. Pine, 3. Diesel","lineage":"","grow_metrics":"","attributes_title":"Euphoric, Happy, Energetic, Creative, Uplifted, Stress, Nausea, Fatigue, Pain, Depression, Dry Mouth, Paranoid, Dry Eyes, Anxious, Dizzy","attributes_num":"width:100%, width:86.1282367447595%, width:84.0937114673243%, width:52.7743526510481%, width:50.924784217016%, width:100%, width:65.395614871306%, width:63.9656816015253%, width:60.6291706387035%, width:40.8007626310772%, width:100%, width:40.8878504672897%, width:29.2056074766355%, width:14.018691588785%, width:3.50467289719626%"}