{"name":"Cinex","description":"Cinex, a hybrid of parents Cinderella 99 and Vortex, has a mixture of flavors ranging from sweet citrus to earthy skunk. The effects are clear-headed and uplifting, perfect for building a positive mindset and stimulating creative energy. Consumers enjoy Cinex for its ability to suppress pain and depression.","flavors":"1. Citrus, 2. Earthy, 3. Pungent","lineage":"","grow_metrics":"Easy, .76-2 m, 251-500, 7-9 wks, 100-200%","attributes_title":"Energetic, Uplifted, Happy, Focused, Euphoric, Depression, Stress, Fatigue, Pain, Headaches, Dry Mouth, Dry Eyes, Anxious, Paranoid, Dizzy","attributes_num":"width:100%, width:97.2041900265565%, width:90.5503098259073%, width:77.7220419002656%, width:70.0354086751254%, width:100%, width:86.5573329748622%, width:69.1356365102836%, width:64.4307030514854%, width:37.0076623202043%, width:100%, width:41.1546200278595%, width:29.2988701439406%, width:27.0391580250735%, width:6.67079399473766%"}