{"name":"Hawaiian Dream","description":"Hawaiian Dream is an uplifting sativa strain that crosses Blue Dream with a Hawaiian variety. Though some renditions of this strain have a THC-dominant chemical profile, Hawaiian Dream is best known for its high CBD content which is often twice as abundant as its THC. Patients look to this high-CBD sativa to remedy pain, inflammation, and anxiety without physical heaviness or a foggy head.","flavors":"1. Sweet, 2. Tropical, 3. Pineapple","lineage":"","grow_metrics":"","attributes_title":"Happy, Relaxed, Focused, Euphoric, Energetic, Depression, Pain, Inflammation, Stress, Fatigue, Dry Mouth, Dizzy, Anxious, Dry Eyes, Paranoid","attributes_num":"width:100%, width:98.1481481481482%, width:91.812865497076%, width:91.0818713450292%, width:77.6315789473684%, width:100%, width:88.8346552776083%, width:73.8865161683954%, width:55.5216595485052%, width:28.4319707138499%, width:100%, width:22.5738396624473%, width:22.5738396624473%, width:19.4092827004219%, width:17.7215189873418%"}