{"name":"Johnny’s Tonic","description":"Johnny’s Tonic is a sativa-dominant California strain bred by Elemental Seeds. It took home a 2014 Cannabis Cup award for its high CBD content inherited from Cannatonic.","flavors":"1. Flowery, 2. Skunk, 3. Pungent","lineage":"","grow_metrics":"","attributes_title":"Happy, Relaxed, Uplifted, Euphoric, Focused, Cramps, Inflammation, Fatigue, Nausea, Pain, Dry Eyes, Dry Mouth","attributes_num":"width:100%, width:88.1578947368421%, width:63.1578947368421%, width:44.7368421052632%, width:44.7368421052632%, width:100%, width:80.8510638297872%, width:70.2127659574468%, width:70.2127659574468%, width:70.2127659574468%, width:100%, width:35.7142857142857%"}