{"name":"Bronze Whaler","description":"An 80/20 indica-dominant strain bred in Australia, Bronze Whaler gives off the sweet smell of fruit with distinct tropical overtones. Awarded 2nd place at the Sydney Cannabis Cup in 2002, this dense, compact bud produces an abundance of fine white pistils that turn to a bronze hue on upon maturing. For patients seeking long-lasting relief from pain and stress, this nighttime strain is ideal.","flavors":"","lineage":"","grow_metrics":"7-9 wks","attributes_title":"Hungry, Relaxed, Stress, Dry Mouth","attributes_num":"width:100%, width:100%, width:100%, width:100%"}