{"name":"Bubba's Gift","description":"Developed by Humboldt Seed Organization, Bubba’s Gift is a strain unlike any other. Despite being almost purely indica, this cross between Bubba Kush and God’s Gift produces functional and uplifting effects with a mild body high. Given its strong indica genetics, this sweet, fruity strain is surprisingly well-suited for daytime creative activities. Bubba’s Gift will flower in 6 weeks and can be grown indoors and outdoors.","flavors":"1. Sweet, 2. Flowery, 3. Berry","lineage":"","grow_metrics":"Easy, .76-2 m, 100-250, 7-9 wks","attributes_title":"Relaxed, Happy, Euphoric, Uplifted, Tingly, Stress, Depression, Insomnia, Headaches, Lack of Appetite, Dry Mouth, Anxious, Dry Eyes, Dizzy, Paranoid","attributes_num":"width:100%, width:88.1630519989548%, width:74.3663443950875%, width:63.0781290828325%, width:31.9832767180559%, width:100%, width:56.3181526619628%, width:42.2065426555484%, width:40.0577293136626%, width:33.8678640153945%, width:100%, width:76.7469879518072%, width:18.1927710843373%, width:13.1325301204819%, width:2.53012048192771%"}