{"name":"Confidential Cheese","description":"Confidential Cheese by DNA Genetics is a crossbred hybrid of Cheese and LA Confidential. This indica-dominant strain has pale green crystal-covered buds with a sour cheese aroma inherited from its parent. Medical patients have used the potent and heavy effects of Confidential Cheese to treat severe pain, insomnia, and lost appetite. For growers, this strain finishes flowering in 8 to 9 weeks with moderate yields.","flavors":"1. Cheese, 2. Pine, 3. Sweet","lineage":"","grow_metrics":"7-9 wks","attributes_title":"Sleepy, Relaxed, Happy, Hungry, Creative, Stress, Pain, Insomnia, Headaches, Cramps, Dry Eyes, Dizzy, Dry Mouth, Anxious, Paranoid","attributes_num":"width:100%, width:95.8287746170678%, width:90.1531728665208%, width:82.9731947483589%, width:74.890590809628%, width:100%, width:99.5908028059236%, width:97.1356196414653%, width:95.4988308651598%, width:61.1067809820733%, width:100%, width:91.6219439475254%, width:65.3846153846154%, width:3.7567084078712%, width:1.25223613595707%"}