{"name":"Digweed","description":"Digweed is an indica-dominant strain that was named after a cat with a sweet tooth for cannabis plants. This high-CBD cross between Afghani and Sweet Tooth has a fruity, floral aroma and is often chosen by patients treating chronic pain, stress, and muscle spasms.","flavors":"1. Earthy, 2. Spicy/Herbal, 3. Skunk","lineage":"","grow_metrics":"7-9 wks","attributes_title":"Happy, Relaxed, Uplifted, Sleepy, Creative, Pain, Stress, Depression, Inflammation, Insomnia, Dry Mouth, Dry Eyes, Dizzy, Paranoid, Anxious","attributes_num":"width:100%, width:89.6551724137931%, width:76.7241379310345%, width:49.1379310344828%, width:45.6896551724138%, width:100%, width:67.8082191780822%, width:57.5342465753425%, width:53.4246575342466%, width:35.6164383561644%, width:100%, width:71.2328767123288%, width:56.1643835616438%, width:21.9178082191781%, width:21.9178082191781%"}