{"name":"Northern Lights #5","description":"Along with Haze and Skunk #1, Northern Lights is among the most influentials strains of all time.  The #5 strain was first entered into competition in 1989.  The strain quickly dominated the Cannabis Cup, winning in '89, '90, and '92.","flavors":"1. Sweet, 2. Pine, 3. Citrus","lineage":"","grow_metrics":"","attributes_title":"Relaxed, Euphoric, Happy, Focused, Uplifted, Pain, Stress, Insomnia, Inflammation, Nausea, Dry Mouth, Dry Eyes, Paranoid, Headache, Dizzy","attributes_num":"width:100%, width:83.3966340290603%, width:80.6648315272309%, width:66.8594724554863%, width:62.9464441269731%, width:100%, width:86.5380700325733%, width:72.0124185667752%, width:69.4370928338762%, width:67.319828990228%, width:100%, width:51.3142857142857%, width:14.4571428571429%, width:7.88571428571428%, width:5.25714285714286%"}