{"name":"Ortega","description":"Ortega by Mr. Nice Seeds is an indica strain bred from Northern Lights genetics. Since its creation in the mid-1980s, Oretga has offered growers heavy yields of resinous, sweet-smelling buds that finish flowering in just 6 to 8 weeks. Its effects are heavily tranquilizing and help to usher in sleep with late night use. ","flavors":"1. Spicy/Herbal, 2. Pepper, 3. Earthy","lineage":"","grow_metrics":"251-500, 7-9 wks","attributes_title":"Relaxed, Giggly, Uplifted, Euphoric, Sleepy, Depression, Pain, Cramps, Eye Pressure, Headaches, Dry Eyes, Dry Mouth","attributes_num":"width:100%, width:83.3333333333333%, width:66.6666666666667%, width:66.6666666666667%, width:50%, width:100%, width:100%, width:66.6666666666667%, width:66.6666666666667%, width:66.6666666666667%, width:100%, width:100%"}