{"name":"Wonder Woman OG","description":"","flavors":"1. Menthol, 2. Citrus, 3. Woody","lineage":"","grow_metrics":"","attributes_title":"Relaxed, Sleepy, Aroused, Tingly, Uplifted, Stress, Insomnia, Pain, Inflammation, Nausea, Dry Mouth, Dry Eyes, Paranoid, Headache","attributes_num":"width:100%, width:79.646017699115%, width:60.1769911504425%, width:51.3274336283186%, width:46.0176991150442%, width:100%, width:75.7281553398058%, width:44.6601941747573%, width:33.9805825242718%, width:33.9805825242718%, width:100%, width:32.0754716981132%, width:7.54716981132076%, width:5.66037735849057%"}